.gitignore
.travis.yml
AUTHORS
CHANGELOG
COPYING.LESSER
LICENSE
MANIFEST.in
README.md
TODO
dev-requirements.txt
requirements.txt
setup.py
docs/sphinx/api.rst
docs/sphinx/conf.py
docs/sphinx/index.rst
docs/sphinx/introduction.rst
extra/sphinx.sh
extra/snippets/file.py
extra/snippets/test.py
tests/.coveragerc
tests/conftest.py
tests/pytest-cov.ini
tests/pytest-pep8.ini
tests/pytest.ini
tests/wasp_general_cache_test.py
tests/wasp_general_command_command_test.py
tests/wasp_general_command_context_test.py
tests/wasp_general_command_template_command_test.py
tests/wasp_general_config_test.py
tests/wasp_general_crypto_aes_test.py
tests/wasp_general_crypto_hash_test.py
tests/wasp_general_crypto_hex_test.py
tests/wasp_general_crypto_hmac_test.py
tests/wasp_general_crypto_kdf_test.py
tests/wasp_general_crypto_random_test.py
tests/wasp_general_crypto_rsa_test.py
tests/wasp_general_datetime_test.py
tests/wasp_general_io_test.py
tests/wasp_general_mime_test.py
tests/wasp_general_network_beacon_beacon_ignore.py
tests/wasp_general_network_beacon_messenger_test.py
tests/wasp_general_network_beacon_task_ignore.py
tests/wasp_general_network_beacon_transport_test.py
tests/wasp_general_network_messenger_coders_test.py
tests/wasp_general_network_messenger_envelope_test.py
tests/wasp_general_network_messenger_layers_test.py
tests/wasp_general_network_messenger_onion_test.py
tests/wasp_general_network_messenger_proto_test.py
tests/wasp_general_network_messenger_session_test.py
tests/wasp_general_network_primitives_test.py
tests/wasp_general_network_transport_test.py
tests/wasp_general_network_web_cookies_ignore.py
tests/wasp_general_network_web_debug_test.py
tests/wasp_general_network_web_headers_test.py
tests/wasp_general_network_web_proto_test.py
tests/wasp_general_network_web_request_test.py
tests/wasp_general_network_web_response_test.py
tests/wasp_general_network_web_service_test.py
tests/wasp_general_network_web_session_test.py
wasp_general.egg-info/PKG-INFO
wasp_general.egg-info/SOURCES.txt
wasp_general.egg-info/dependency_links.txt
wasp_general.egg-info/not-zip-safe
wasp_general.egg-info/requires.txt
wasp_general.egg-info/top_level.txt
