Metadata-Version: 1.1
Name: wasp-general
Version: 0.0.3.3
Summary: Collection of unrelated functions and classes widely used across different wasp-projects
Home-page: https://github.com/a1ezzz/wasp-general
Author: Ildar Gafurov
Author-email: dev@binblob.com
License: GNU Lesser General Public License v3
Keywords: wasp,cli,network,lvm,threads,validation
Platform: UNKNOWN
Classifier: Development Status :: 2 - Pre-Alpha
Classifier: Intended Audience :: Developers
Classifier: License :: OSI Approved :: GNU General Public License v3 (GPLv3)
Classifier: Operating System :: OS Independent
Classifier: Programming Language :: Python
Classifier: Programming Language :: Python :: 3.4
Classifier: Programming Language :: Python :: 3.5
Classifier: Programming Language :: Python :: 3.6
Classifier: Programming Language :: Python :: 3 :: Only
Classifier: Topic :: Software Development :: Libraries
Classifier: Topic :: Software Development :: Libraries :: Python Modules
